bytedpyvelox/__init__.py
bytedpyvelox-0.0.1.dist-info/METADATA
bytedpyvelox-0.0.1.dist-info/WHEEL
bytedpyvelox-0.0.1.dist-info/top_level.txt
bytedpyvelox-0.0.1.dist-info/RECORD
